README.rst
bananaleaf.zip
screenshot.png
setup.py
docs/HISTORY.txt
docs/INSTALL.txt
docs/LICENSE.GPL
docs/LICENSE.txt
plonetheme/__init__.py
plonetheme.bananaleaf.egg-info/PKG-INFO
plonetheme.bananaleaf.egg-info/SOURCES.txt
plonetheme.bananaleaf.egg-info/dependency_links.txt
plonetheme.bananaleaf.egg-info/entry_points.txt
plonetheme.bananaleaf.egg-info/namespace_packages.txt
plonetheme.bananaleaf.egg-info/requires.txt
plonetheme.bananaleaf.egg-info/top_level.txt
plonetheme/bananaleaf/__init__.py
plonetheme/bananaleaf/configure.zcml
plonetheme/bananaleaf/profiles/default/metadata.xml
plonetheme/bananaleaf/profiles/default/theme.xml
plonetheme/bananaleaf/static/index.html
plonetheme/bananaleaf/static/license.txt
plonetheme/bananaleaf/static/manifest.cfg
plonetheme/bananaleaf/static/rules.xml
plonetheme/bananaleaf/static/style.css
plonetheme/bananaleaf/static/images/img01.jpg
plonetheme/bananaleaf/static/images/img02.gif
plonetheme/bananaleaf/static/images/img03.jpg
plonetheme/bananaleaf/static/images/img04.jpg
plonetheme/bananaleaf/static/images/img05.gif
plonetheme/bananaleaf/static/images/img06.gif
plonetheme/bananaleaf/static/images/img07.gif